carpo_teacher/__init__.py
carpo_teacher/_version.py
carpo_teacher/handlers.py
carpo_teacher/labextension/build_log.json
carpo_teacher/labextension/package.json
carpo_teacher/labextension/schemas/carpo-teacher/package.json.orig
carpo_teacher/labextension/schemas/carpo-teacher/plugin.json
carpo_teacher/labextension/static/lib_index_js.26b2dac9fb26b92e5e77.js
carpo_teacher/labextension/static/lib_index_js.26b2dac9fb26b92e5e77.js.map
carpo_teacher/labextension/static/lib_index_js.319b732eeb1666ec582d.js
carpo_teacher/labextension/static/lib_index_js.319b732eeb1666ec582d.js.map
carpo_teacher/labextension/static/lib_index_js.50f4eea05f2e4a5b45b2.js
carpo_teacher/labextension/static/lib_index_js.50f4eea05f2e4a5b45b2.js.map
carpo_teacher/labextension/static/lib_index_js.52016ae45df3354154d1.js
carpo_teacher/labextension/static/lib_index_js.52016ae45df3354154d1.js.map
carpo_teacher/labextension/static/lib_index_js.5917b7702f19b60e369b.js
carpo_teacher/labextension/static/lib_index_js.5917b7702f19b60e369b.js.map
carpo_teacher/labextension/static/lib_index_js.63bb1f0b3e113fb2d1b6.js
carpo_teacher/labextension/static/lib_index_js.63bb1f0b3e113fb2d1b6.js.map
carpo_teacher/labextension/static/lib_index_js.7d74b1f97a0b149a3046.js
carpo_teacher/labextension/static/lib_index_js.7d74b1f97a0b149a3046.js.map
carpo_teacher/labextension/static/lib_index_js.8c1925dc16fef5f68832.js
carpo_teacher/labextension/static/lib_index_js.8c1925dc16fef5f68832.js.map
carpo_teacher/labextension/static/lib_index_js.8fb15209cdd37bf033ce.js
carpo_teacher/labextension/static/lib_index_js.8fb15209cdd37bf033ce.js.map
carpo_teacher/labextension/static/lib_index_js.ebd7d82c9b8637d2bba0.js
carpo_teacher/labextension/static/lib_index_js.ebd7d82c9b8637d2bba0.js.map
carpo_teacher/labextension/static/lib_index_js.f7d1294a5b7123ce3525.js
carpo_teacher/labextension/static/lib_index_js.f7d1294a5b7123ce3525.js.map
carpo_teacher/labextension/static/remoteEntry.4b73dfef64c743b2f878.js
carpo_teacher-0.2.3.dist-info/licenses/LICENSE
carpo_teacher-0.2.3.dist-info/METADATA
carpo_teacher-0.2.3.dist-info/WHEEL
carpo_teacher-0.2.3.dist-info/top_level.txt
carpo_teacher-0.2.3.dist-info/RECORD
