Metadata-Version: 2.4
Name: carpo_teacher
Version: 0.2.3
Summary: JupyterLab extension with backend and frontend part for carpo teacher.
Home-page: https://github.com/github_username/carpo-teacher
Author: test
Author-email: test@test.com
License: BSD 3-Clause License
Keywords: Jupyter,JupyterLab,JupyterLab4
Platform: Linux
Platform: Mac OS X
Platform: Windows
Classifier: Framework :: Jupyter
Classifier: Framework :: Jupyter :: JupyterLab
Classifier: Framework :: Jupyter :: JupyterLab :: 4
Classifier: Framework :: Jupyter :: JupyterLab :: Extensions
Classifier: Framework :: Jupyter :: JupyterLab :: Extensions :: Prebuilt
Classifier: License :: OSI Approved :: BSD License
Classifier: Programming Language :: Python
Classifier: Programming Language :: Python :: 3
Classifier: Programming Language :: Python :: 3.9
Classifier: Programming Language :: Python :: 3.10
Classifier: Programming Language :: Python :: 3.11
Classifier: Programming Language :: Python :: 3.12
Classifier: Programming Language :: Python :: 3.13
Requires-Python: >=3.7
License-File: LICENSE
Dynamic: author
Dynamic: author-email
Dynamic: home-page
Dynamic: keywords
Dynamic: license-file
Dynamic: platform
Dynamic: requires-python
Dynamic: summary
